galaxy/proc/__init__.py
galaxy/proc/constant.py
galaxy/proc/controller.py
galaxy/proc/multi.py
galaxy/proc/proc.py
galaxy/proc/scheduler.py
galaxy/proc/threadproc.py
galaxy_py_proc-0.0.9.dist-info/AUTHORS
galaxy_py_proc-0.0.9.dist-info/COPYING.md
galaxy_py_proc-0.0.9.dist-info/LICENSE.txt
galaxy_py_proc-0.0.9.dist-info/METADATA
galaxy_py_proc-0.0.9.dist-info/WHEEL
galaxy_py_proc-0.0.9.dist-info/RECORD
